envawareconfig/__init__.py
envawareconfig/errors.py
envawareconfig/expand_variables.py
envawareconfig/load_config.py
envawareconfig-0.2.1.dist-info/WHEEL
envawareconfig-0.2.1.dist-info/METADATA
envawareconfig-0.2.1.dist-info/RECORD
