Metadata-Version: 2.1
Name: envawareconfig
Version: 0.2.1
Summary: Load configurations from yaml files with automatic environment variable substitution
Home-page: https://github.com/mfrattini7/envawareconfig
Author: marcello
Author-email: marcello.frattini7@gmail.com
Requires-Python: >=3.9,<4.0
Classifier: Programming Language :: Python :: 3
Classifier: Programming Language :: Python :: 3.10
Classifier: Programming Language :: Python :: 3.9
Requires-Dist: PyYAML (>=6.0,<7.0)
Requires-Dist: python-dotenv (>=0.19.2,<0.20.0)
Project-URL: Repository, https://github.com/mfrattini7/envawareconfig
